Metadata-Version: 1.0
Name: stats-dists
Version: 1.1
Summary: Gaussian distributions and Binomial
Home-page: UNKNOWN
Author: Ahmad Muhammad Tahir
Author-email: ahmad.tahir49@yahoo.com
License: UNKNOWN
Platform: UNKNOWN
